{
  "id": "xananode.hugo:source/artifact-static-js-viewer-engine",
  "title": "Static / Js / Viewer Engine",
  "type": "source",
  "subtype": "renderer_asset",
  "importance": 3,
  "summary": "static/js/viewer-engine.js is preserved as a raw Hugo source artifact in the XanaNode Hugo substrate.",
  "source_url": "https://github.com/kingc95/XanaNode-Hugo/blob/main/static/js/viewer-engine.js",
  "artifact_path": "static/js/viewer-engine.js",
  "asset_path": "assets/raw/repository/static/js/viewer-engine.js",
  "asset_role": "repository_source",
  "media_type": "document",
  "mime_type": "text/plain",
  "rights_status": "Apache-2.0",
  "content_id": "sha256:cc3858cedd795c5a60fac24a0c926050188da69114a9b02c455cff7759931cc0",
  "content": "import {\n  buildHopNeighborhood,\n  findProjectionRoute,\n  layoutReadableProjection\n} from \"./projection.js\";\n\nexport const DEFAULT_VIEWER_SEARCH_STOPWORDS = new Set([\n  \"a\", \"an\", \"and\", \"are\", \"as\", \"at\", \"be\", \"by\", \"for\", \"from\", \"how\",\n  \"do\", \"does\", \"he\", \"i\", \"in\", \"into\", \"is\", \"it\", \"me\", \"my\", \"of\", \"on\", \"or\", \"please\",\n  \"show\", \"tell\", \"that\", \"the\", \"their\", \"them\", \"this\", \"to\", \"want\",\n  \"was\", \"what\", \"when\", \"where\", \"which\", \"who\", \"why\", \"with\", \"you\",\n  \"your\", \"about\", \"find\", \"search\", \"trace\", \"follow\", \"explain\"\n]);\n\nexport const DEFAULT_VIEWER_RELATIONSHIP_PRIORITY = {\n  defines: 10,\n  created: 9,\n  created_by: 9,\n  originated_by: 9,\n  coined: 9,\n  represented_by: 9,\n  used_as_primary_media_for: 9,\n  depicts: 9,\n  participated_in: 8,\n  authored: 8,\n  features: 8,\n  featured_in: 8,\n  presented: 8,\n  presented_by: 8,\n  proposed: 7,\n  demonstrates: 7,\n  demonstrated_by: 7,\n  explains: 7,\n  explained_by: 7,\n  context_for: 6,\n  documents: 6,\n  extends: 6,\n  supports: 6,\n  supported_by: 6,\n  contrasts: 6,\n  depends_on: 6,\n  exposes: 6,\n  anticipates: 6,\n  contains: 6,\n  includes: 6,\n  uses: 5,\n  used_by: 5,\n  cites: 5,\n  related_to: 4,\n  related: 3,\n  mentions: 1,\n  unresolved_media: 1\n};\n\nexport const MIN_VIEWER_SEARCH_QUERY_LENGTH = 3;\nexport const DEFAULT_VIEWER_TOUR_SETTINGS = Object.freeze({\n  mode: \"narration\",\n  voice: \"\",\n  rate: 1,\n  pitch: 1,\n  detail: \"title-summary-content\",\n  timedSeconds: 9\n});\n\nexport function normalizeViewerTourSettings(value = {}) {\n  const next = {\n    ...DEFAULT_VIEWER_TOUR_SETTINGS,\n    ...(value && typeof value === \"object\" ? value : {})\n  };\n  next.mode = next.mode === \"timed\" ? \"timed\" : \"narration\";\n  next.voice = String(next.voice || \"\");\n  next.rate = Math.max(0.65, Math.min(1.55, Number(next.rate) || DEFAULT_VIEWER_TOUR_SETTINGS.rate));\n  next.pitch = Math.max(0.75, Math.min(1.35, Number(next.pitch) || DEFAULT_VIEWER_TOUR_SETTINGS.pitch));\n  next.timedSeconds = Math.max(3, Math.min(120, Number(next.timedSeconds) || DEFAULT_VIEWER_TOUR_SETTINGS.timedSeconds));\n  if (![\"title-only\", \"title-summary\", \"title-summary-content\", \"full\"].includes(next.detail)) {\n    next.detail = DEFAULT_VIEWER_TOUR_SETTINGS.detail;\n  }\n  return next;\n}\n\nexport function getViewerTimedDwellMs(settings = {}) {\n  const resolved = normalizeViewerTourSettings(settings);\n  return Math.max(3000, Math.min(120000, resolved.timedSeconds * 1000));\n}\n\nexport function normalizeSearchText(value) {\n  return String(value || \"\")\n    .toLowerCase()\n    .normalize(\"NFKD\")\n    .replace(/[\\u0300-\\u036f]/g, \"\")\n    .replace(/[^\\w\\s.-]/g, \" \")\n    .replace(/\\s+/g, \" \")\n    .trim();\n}\n\nexport function stripSearchLeadIn(value) {\n  let next = String(value || \"\").trim();\n  const prefixes = [\n    /^who\\s+is\\s+/,\n    /^what\\s+is\\s+/,\n    /^what\\s+are\\s+/,\n    /^tell\\s+me\\s+about\\s+/,\n    /^show\\s+me\\s+/,\n    /^find\\s+/,\n    /^search\\s+for\\s+/,\n    /^i\\s+want\\s+to\\s+know\\s+about\\s+/,\n    /^can\\s+you\\s+find\\s+/,\n    /^where\\s+is\\s+/,\n    /^why\\s+is\\s+/,\n    /^how\\s+does\\s+/,\n    /^how\\s+do\\s+/,\n    /^give\\s+me\\s+/,\n    /^trace\\s+/,\n    /^follow\\s+/\n  ];\n\n  for (const pattern of prefixes) {\n    next = next.replace(pattern, \"\");\n  }\n\n  return next.trim();\n}\n\nexport function tokenizeSearch(value) {\n  return normalizeSearchText(value)\n    .split(/\\s+/)\n    .map((token) => token.trim())\n    .filter((token) => token.length >= 2);\n}\n\nexport function buildSearchPlan(value, options = {}) {\n  const stopwords = options.stopwords || DEFAULT_VIEWER_SEARCH_STOPWORDS;\n  const raw = String(value || \"\").trim();\n  const normalizedRaw = normalizeSearchText(raw);\n  const conversational = stripSearchLeadIn(normalizedRaw);\n  const rawTokens = tokenizeSearch(conversational);\n  const filteredTokens = rawTokens.filter((token) => !stopwords.has(token));\n  const finalTokens = filteredTokens.length ? filteredTokens : rawTokens;\n  const normalized = finalTokens.join(\" \").trim();\n\n  return {\n    raw,\n    normalized,\n    tokens: finalTokens,\n    display: normalized || normalizedRaw || raw\n  };\n}\n\nexport function shouldRunViewerSearch(value, minLength = MIN_VIEWER_SEARCH_QUERY_LENGTH) {\n  return String(value || \"\").trim().length >= Math.max(1, Number(minLength) || MIN_VIEWER_SEARCH_QUERY_LENGTH);\n}\n\nexport function buildViewerSearchState(nodes = [], value = \"\", options = {}) {\n  const raw = String(value || \"\");\n  const trimmed = raw.trim();\n  const minLength = Math.max(1, Number(options.minLength) || MIN_VIEWER_SEARCH_QUERY_LENGTH);\n  if (!trimmed) {\n    return {\n      input: raw,\n      query: \"\",\n      ready: false,\n      pending: false,\n      plan: { display: \"\" },\n      results: [],\n      error: null,\n      meta: \"\"\n    };\n  }\n\n  if (!shouldRunViewerSearch(trimmed, minLength)) {\n    return {\n      input: raw,\n      query: \"\",\n      ready: false,\n      pending: true,\n      plan: { display: trimmed },\n      results: [],\n      error: null,\n      meta: `Keep typing. Search starts after ${minLength} characters.`\n    };\n  }\n\n  try {\n    const next = searchViewerNodes(nodes, trimmed, options);\n    return {\n      ...next,\n      input: raw,\n      query: trimmed,\n      ready: true,\n      pending: false,\n      error: null,\n      meta: next.results?.length\n        ? `${next.results.length} match${next.results.length === 1 ? \"\" : \"es\"} for ${next.plan?.display || trimmed}`\n        : `No matches for ${next.plan?.display || trimmed}.`\n    };\n  } catch (error) {\n    return {\n      input: raw,\n      query: trimmed,\n      ready: true,\n      pending: false,\n      plan: { display: trimmed },\n      results: [],\n      error: error instanceof Error ? error.message : String(error),\n      meta: `Search paused: ${error instanceof Error ? error.message : String(error)}`\n    };\n  }\n}\n\nexport function stripViewerHtml(value) {\n  return String(value || \"\").replace(/<[^>]+>/g, \" \");\n}\n\nfunction trimViewerSearchSource(value, maxLength = 1200) {\n  const text = String(value || \"\").replace(/\\s+/g, \" \").trim();\n  if (text.length <= maxLength) return text;\n  return `${text.slice(0, maxLength)}...`;\n}\n\nexport function buildViewerNodeSearchText(node = {}) {\n  return normalizeSearchText([\n    node.id,\n    node.title,\n    node.type,\n    node.summary,\n    trimViewerSearchSource(node.content),\n    trimViewerSearchSource(stripViewerHtml(node.html || \"\")),\n    node.url,\n    node.youtube_url,\n    node.primary_media_node?.youtube_url,\n    node.youtube_url ? \"youtube video\" : \"\",\n    node.primary_media_node?.youtube_url ? \"youtube video\" : \"\",\n    node.media_type,\n    node.creator,\n    node.source_name,\n    node.rights_status,\n    node.caption,\n    Array.isArray(node.tags) ? node.tags.join(\" \") : \"\",\n    Array.isArray(node.aliases) ? node.aliases.join(\" \") : \"\"\n  ].filter(Boolean).join(\" \"));\n}\n\nexport function scoreViewerSearchResult(node = {}, haystack = \"\", normalizedQuery = \"\", queryTokens = []) {\n  let score = 0;\n  if (!haystack) return 0;\n\n  const title = normalizeSearchText(node.title || \"\");\n  const id = normalizeSearchText(node.id || \"\");\n  const summary = normalizeSearchText(node.summary || \"\");\n\n  if (id === normalizedQuery) score += 120;\n  if (title === normalizedQuery) score += 100;\n  if (title.includes(normalizedQuery)) score += 70;\n  if (id.includes(normalizedQuery)) score += 55;\n  if (summary.includes(normalizedQuery)) score += 35;\n  if (haystack.includes(normalizedQuery)) score += 25;\n\n  queryTokens.forEach((token) => {\n    if (title.includes(token)) score += 18;\n    if (id.includes(token)) score += 14;\n    if (summary.includes(token)) score += 10;\n    if (haystack.includes(token)) score += 5;\n  });\n\n  const tokenMatches = queryTokens.filter((token) =>\n    title.includes(token)\n    || id.includes(token)\n    || summary.includes(token)\n    || haystack.includes(token)\n  ).length;\n\n  if (queryTokens.length) {\n    const coverage = tokenMatches / queryTokens.length;\n    score += coverage * 40;\n    if (queryTokens.length >= 3 && coverage < 0.34) score -= 18;\n    if (queryTokens.length >= 5 && coverage < 0.2) score -= 30;\n  }\n\n  score += Number(node.importance || 0);\n  return score;\n}\n\nexport function makeViewerSearchSnippet(node = {}, queryTokens = []) {\n  const source = stripViewerHtml(node.summary || node.content || node.html || \"\");\n  const text = source.replace(/\\s+/g, \" \").trim();\n  if (!text) return \"\";\n\n  const lower = text.toLowerCase();\n  const firstMatch = queryTokens\n    .map((token) => lower.indexOf(token))\n    .filter((index) => index >= 0)\n    .sort((a, b) => a - b)[0];\n\n  if (firstMatch === undefined) {\n    return text.length > 140 ? `${text.slice(0, 140)}...` : text;\n  }\n\n  const start = Math.max(0, firstMatch - 50);\n  const end = Math.min(text.length, firstMatch + 90);\n  const snippet = text.slice(start, end).trim();\n  const prefix = start > 0 ? \"...\" : \"\";\n  const suffix = end < text.length ? \"...\" : \"\";\n  return `${prefix}${snippet}${suffix}`;\n}\n\nexport function searchViewerNodes(nodes = [], query = \"\", options = {}) {\n  const searchPlan = buildSearchPlan(query, options);\n  if (!searchPlan.display) {\n    return { plan: searchPlan, results: [] };\n  }\n\n  const normalizedQuery = searchPlan.display;\n  const queryTokens = searchPlan.tokens;\n  const limit = Math.max(1, Number(options.limit || 30));\n\n  const results = nodes\n    .map((node) => {\n      const haystack = buildViewerNodeSearchText(node);\n      const score = scoreViewerSearchResult(node, haystack, normalizedQuery, queryTokens);\n      return {\n        node,\n        score,\n        snippet: makeViewerSearchSnippet(node, queryTokens)\n      };\n    })\n    .filter((result) => result.score > 0)\n    .sort((a, b) => {\n      if (b.score !== a.score) return b.score - a.score;\n      const aImportance = Number(a.node.importance || 0);\n      const bImportance = Number(b.node.importance || 0);\n      if (bImportance !== aImportance) return bImportance - aImportance;\n      return String(a.node.title || \"\").localeCompare(String(b.node.title || \"\"));\n    })\n    .slice(0, limit);\n\n  return { plan: searchPlan, results };\n}\n\nexport function resolveViewerNodeSelection(query, allNodes = []) {\n  const raw = String(query || \"\").trim();\n  if (!raw) return null;\n\n  const rawLower = raw.toLowerCase();\n  const normalized = normalizeSearchText(raw);\n  return allNodes.find((node) => {\n    if (!node) return false;\n    const id = String(node.id || \"\").toLowerCase();\n    const titleNormalized = normalizeSearchText(node.title || \"\");\n    return id === rawLower\n      || titleNormalized === normalized\n      || normalizeSearchText(node.id || \"\") === normalized;\n  }) || null;\n}\n\nfunction normalizeViewerRef(value, normalizeId) {\n  if (!value) return \"\";\n  return typeof normalizeId === \"function\"\n    ? String(normalizeId(value) || \"\").trim()\n    : String(value || \"\").trim();\n}\n\nfunction makeViewerIdPredicate(nodeIds, normalizeId) {\n  if (nodeIds instanceof Set) {\n    return (value) => nodeIds.has(normalizeViewerRef(value, normalizeId));\n  }\n  if (Array.isArray(nodeIds)) {\n    const asSet = new Set(nodeIds.map((value) => normalizeViewerRef(value, normalizeId)).filter(Boolean));\n    return (value) => asSet.has(normalizeViewerRef(value, normalizeId));\n  }\n  return () => true;\n}\n\nfunction uniqueViewerIds(values = [], normalizeId) {\n  const ids = [];\n  values.forEach((value) => {\n    const id = normalizeViewerRef(value, normalizeId);\n    if (id && !ids.includes(id)) ids.push(id);\n  });\n  return ids;\n}\n\nexport function getViewerTrailNodeIds(node = {}, options = {}) {\n  const normalizeId = options.normalizeId;\n  const hasAllowedId = makeViewerIdPredicate(options.nodeIds, normalizeId);\n  const allEdges = Array.isArray(options.allEdges) ? options.allEdges : [];\n  const directValues = Array.isArray(node.nodes)\n    ? node.nodes\n    : Array.isArray(node.trail_nodes)\n      ? node.trail_nodes\n      : [];\n  const explicitIds = uniqueViewerIds(directValues, normalizeId).filter((id) => hasAllowedId(id));\n  if (explicitIds.length) return explicitIds;\n\n  const nodeId = normalizeViewerRef(node.id, normalizeId);\n  if (!nodeId) return [];\n\n  const outgoingTrailEdges = allEdges.filter((edge) => {\n    const sourceId = normalizeViewerRef(edge?.source, normalizeId);\n    const targetId = normalizeViewerRef(edge?.target, normalizeId);\n    return sourceId === nodeId\n      && targetId\n      && hasAllowedId(targetId)\n      && (edge?.origin === \"trail\" || edge?.type === \"starts_with\" || edge?.type === \"continues_to\");\n  });\n\n  const directTargets = uniqueViewerIds(outgoingTrailEdges.map((edge) => edge.target), normalizeId);\n  const leadEdge = outgoingTrailEdges.find((edge) => edge?.type === \"starts_with\")\n    || outgoingTrailEdges.find((edge) => edge?.type === \"continues_to\")\n    || null;\n  const leadId = normalizeViewerRef(leadEdge?.target, normalizeId);\n  if (!leadId) return directTargets;\n\n  const sequence = [];\n  const seen = new Set();\n  let currentId = leadId;\n  while (currentId && !seen.has(currentId) && hasAllowedId(currentId)) {\n    sequence.push(currentId);\n    seen.add(currentId);\n    const nextEdge = allEdges.find((edge) => {\n      const sourceId = normalizeViewerRef(edge?.source, normalizeId);\n      const targetId = normalizeViewerRef(edge?.target, normalizeId);\n      return sourceId === currentId\n        && targetId\n        && hasAllowedId(targetId)\n        && edge?.type === \"continues_to\";\n    });\n    currentId = normalizeViewerRef(nextEdge?.target, normalizeId);\n  }\n\n  return sequence.length ? sequence : directTargets;\n}\n\nexport function getViewerTrailBranches(node = {}, options = {}) {\n  const normalizeId = options.normalizeId;\n  const hasAllowedId = makeViewerIdPredicate(options.nodeIds, normalizeId);\n  const branches = Array.isArray(node.trail_branches)\n    ? node.trail_branches\n    : Array.isArray(node.branches)\n      ? node.branches\n      : [];\n  if (!Array.isArray(branches)) return [];\n\n  return branches\n    .map((branch) => ({\n      after: normalizeViewerRef(branch?.after, normalizeId),\n      prompt: String(branch?.prompt || \"Choose the next path\"),\n      choices: Array.isArray(branch?.choices)\n        ? branch.choices\n          .map((choice) => ({\n            label: String(choice?.label || \"Continue\"),\n            summary: String(choice?.summary || \"\"),\n            nodes: uniqueViewerIds(choice?.nodes || [], normalizeId).filter((id) => hasAllowedId(id))\n          }))\n          .filter((choice) => choice.nodes.length)\n        : []\n    }))\n    .filter((branch) => branch.after && branch.choices.length);\n}\n\nexport function getViewerTrailPlaylistNodeIds(node = {}, options = {}) {\n  const ids = [];\n  const push = (value) => {\n    const id = normalizeViewerRef(value, options.normalizeId);\n    if (id && !ids.includes(id)) ids.push(id);\n  };\n\n  getViewerTrailNodeIds(node, options).forEach(push);\n  getViewerTrailBranches(node, options).forEach((branch) => {\n    branch.choices.forEach((choice) => choice.nodes.forEach(push));\n  });\n\n  return ids;\n}\n\nexport function findViewerTrailContext(node = {}, allNodes = [], options = {}) {\n  if (!node) return null;\n  if (node.type === \"trail\") return node;\n  const nodeId = normalizeViewerRef(node.id, options.normalizeId);\n  if (!nodeId) return null;\n  return allNodes.find((candidate) => {\n    if (!candidate || candidate.type !== \"trail\") return false;\n    return getViewerTrailPlaylistNodeIds(candidate, options).includes(nodeId);\n  }) || null;\n}\n\nexport function buildViewerTrailPlaybackState(trailNode = {}, options = {}) {\n  const nodes = getViewerTrailNodeIds(trailNode, options);\n  if (!nodes.length) return null;\n  return {\n    trailId: normalizeViewerRef(trailNode.id, options.normalizeId),\n    nodes,\n    index: Math.max(0, Number(options.startIndex || 0)),\n    branches: getViewerTrailBranches(trailNode, options),\n    branchChoices: { ...(options.branchChoices || {}) },\n    playback: Boolean(options.playback)\n  };\n}\n\nexport function buildViewerActiveTrail(node = {}, options = {}) {\n  return buildViewerTrailPlaybackState(node, options);\n}\n\nexport function createViewerTourSession(options = {}) {\n  const focusId = normalizeViewerRef(options.focusId, options.normalizeId);\n  return {\n    tourIndex: 0,\n    previousFocusId: \"\",\n    tourVisited: focusId ? [focusId] : [],\n    tourRecent: focusId ? [focusId] : [],\n    activeTrail: options.trailNode\n      ? buildViewerActiveTrail(options.trailNode, options.trailOptions || {})\n      : null\n  };\n}\n\nexport function pickNextViewerTrailNode(activeTrail = {}, focusId = \"\", options = {}) {\n  if (!activeTrail?.nodes?.length) {\n    return { nextId: null, trail: activeTrail, branch: null, done: true };\n  }\n\n  const normalizedFocusId = normalizeViewerRef(focusId, options.normalizeId);\n  const branch = activeTrail.branches?.find((candidate) => {\n    return candidate.after === normalizedFocusId && !activeTrail.branchChoices?.[candidate.after];\n  }) || null;\n  if (branch) {\n    return { nextId: null, trail: activeTrail, branch, done: false };\n  }\n\n  const currentIndex = activeTrail.nodes.indexOf(normalizedFocusId);\n  const nextIndex = currentIndex >= 0 ? currentIndex + 1 : Number(activeTrail.index || 0);\n  const nextId = activeTrail.nodes[nextIndex] || null;\n  return {\n    nextId,\n    trail: {\n      ...activeTrail,\n      index: nextIndex + 1\n    },\n    branch: null,\n    done: !nextId\n  };\n}\n\nexport function applyViewerTrailBranchChoice(activeTrail = {}, afterId = \"\", choice = {}, options = {}) {\n  return {\n    ...activeTrail,\n    nodes: uniqueViewerIds(choice?.nodes || [], options.normalizeId),\n    index: 0,\n    branchChoices: {\n      ...(activeTrail.branchChoices || {}),\n      [normalizeViewerRef(afterId, options.normalizeId)]: String(choice?.label || \"Continue\")\n    }\n  };\n}\n\nexport function rememberViewerTourVisit(nodeId = \"\", options = {}) {\n  const normalized = normalizeViewerRef(nodeId, options.normalizeId);\n  const recentLimit = Math.max(1, Number(options.recentLimit) || 7);\n  const resetFloor = Math.max(1, Number(options.resetFloor) || 8);\n  const resetRatio = Math.max(0.1, Math.min(1, Number(options.resetRatio) || 0.7));\n  const visibleCount = Math.max(0, Number(options.visibleCount) || 0);\n  const visited = uniqueViewerIds(options.tourVisited || [], options.normalizeId);\n  const recent = uniqueViewerIds(options.tourRecent || [], options.normalizeId);\n\n  if (normalized && !visited.includes(normalized)) visited.push(normalized);\n  const nextRecent = normalized\n    ? [...recent.filter((entry) => entry !== normalized), normalized].slice(-recentLimit)\n    : recent.slice(-recentLimit);\n\n  let nextVisited = visited;\n  if (visibleCount > 0 && nextVisited.length > Math.max(resetFloor, Math.floor(visibleCount * resetRatio))) {\n    nextVisited = [...nextRecent];\n  }\n\n  return {\n    tourVisited: nextVisited,\n    tourRecent: nextRecent\n  };\n}\n\nexport function getViewerTrailLeadId(node = {}, options = {}) {\n  const trailNodes = getViewerTrailNodeIds(node, options);\n  if (node?.type === \"trail\" && trailNodes.length) return trailNodes[0];\n  const normalizeId = options.normalizeId;\n  const nodeId = normalizeViewerRef(node?.id, normalizeId);\n  if (!nodeId) return \"\";\n  const leadEdge = (options.allEdges || []).find((edge) => {\n    const sourceId = normalizeViewerRef(edge?.source, normalizeId);\n    return sourceId === nodeId && (edge?.type === \"starts_with\" || edge?.type === \"continues_to\");\n  });\n  return normalizeViewerRef(leadEdge?.target, normalizeId);\n}\n\nexport function nodeSubtypeValues(node) {\n  if (!node) return [];\n  const values = [];\n  const push = (value) => {\n    if (!value) return;\n    const text = String(value).trim();\n    if (text && !values.includes(text)) values.push(text);\n  };\n\n  push(node.subtype);\n  if (Array.isArray(node.subtypes)) node.subtypes.forEach(push);\n  if (Array.isArray(node.additional_subtypes)) node.additional_subtypes.forEach(push);\n  if (Array.isArray(node.facets)) node.facets.forEach(push);\n  return values;\n}\n\nexport function scoreViewerEdge(edge, allNodes = [], focusId, options = {}) {\n  const relationshipPriority = {\n    ...DEFAULT_VIEWER_RELATIONSHIP_PRIORITY,\n    ...(options.relationshipPriority || {})\n  };\n  const source = allNodes.find((node) => node.id === edge.source);\n  const target = allNodes.find((node) => node.id === edge.target);\n  const sourceImportance = Number(source?.importance || 3);\n  const targetImportance = Number(target?.importance || 3);\n  const weight = Number(edge.weight || 1);\n  const typePriority = relationshipPriority[edge.type] || 3;\n  const directBonus = edge.source === focusId || edge.target === focusId ? 20 : 0;\n  const explicitBonus = edge.origin === \"relationship\" ? 8 : 0;\n  const visibilityBonus = edge.visibility === \"primary\" ? 5 : edge.visibility === \"secondary\" ? 2 : 0;\n  return directBonus + explicitBonus + visibilityBonus + weight * 10 + typePriority + sourceImportance + targetImportance;\n}\n\nfunction asSetLike(values, fallback = null) {\n  if (values instanceof Set) return values;\n  if (Array.isArray(values)) return new Set(values);\n  return fallback;\n}\n\nexport function buildVisibleSubgraph(allNodes = [], allEdges = [], options = {}) {\n  const {\n    focusId = \"\",\n    maxDepth = 1,\n    enabledTypes,\n    enabledMediaTypes,\n    enabledRelationshipTypes,\n    enabledSubtypes,\n    nodeFilter,\n    edgeFilter,\n    edgeScore,\n    exhaustive = false\n  } = options;\n\n  const typeSet = asSetLike(enabledTypes);\n  const mediaTypeSet = asSetLike(enabledMediaTypes);\n  const relationshipTypeSet = asSetLike(enabledRelationshipTypes);\n  const subtypeSet = asSetLike(enabledSubtypes);\n\n  function defaultNodeFilter(node) {\n    if (node.id === focusId) return true;\n    if (typeSet && !typeSet.has(node.type)) return false;\n    const subtypes = nodeSubtypeValues(node);\n    if (subtypeSet && subtypes.length && !subtypes.some((value) => subtypeSet.has(value))) return false;\n    if (node.type === \"media\" && mediaTypeSet) {\n      return mediaTypeSet.has(node.media_type || \"image\");\n    }\n    return true;\n  }\n\n  function defaultEdgeFilter(edge) {\n    if (!relationshipTypeSet) return true;\n    return relationshipTypeSet.has(edge.type || \"related_to\");\n  }\n\n  return buildHopNeighborhood(allNodes, allEdges, {\n    focusId,\n    maxDepth,\n    exhaustive,\n    nodeFilter: (node) => defaultNodeFilter(node) && (nodeFilter ? nodeFilter(node) : true),\n    edgeFilter: (edge) => defaultEdgeFilter(edge) && (edgeFilter ? edgeFilter(edge) : true),\n    edgeScore: edgeScore || ((edge) => scoreViewerEdge(edge, allNodes, focusId))\n  });\n}\n\nexport function buildViewerGraphModel(allNodes = [], allEdges = [], options = {}) {\n  const {\n    focusId = \"\",\n    maxDepth = 1,\n    registry = null,\n    width = 900,\n    height = 620,\n    labelForEdge = null\n  } = options;\n  const visible = buildVisibleSubgraph(allNodes, allEdges, options);\n  const graph = layoutReadableProjection(visible, {\n    focusId,\n    registry,\n    width,\n    height,\n    maxDepth,\n    labelForEdge\n  });\n  return { visible, graph };\n}\n\nexport function buildViewerTravelPlan(graphModel, currentId, nextId, options = {}) {\n  if (!graphModel || !currentId || !nextId) return null;\n  const currentNode = graphModel.nodes?.find((node) => node.id === currentId) || null;\n  const nextNode = graphModel.nodes?.find((node) => node.id === nextId) || null;\n  const route = findProjectionRoute(graphModel.edges || [], currentId, nextId, {\n    maxDepth: options.maxDepth || 4\n  });\n  const routeNodes = (route?.nodeIds || [])\n    .map((id) => graphModel.nodes?.find((node) => node.id === id))\n    .filter(Boolean);\n  return { currentNode, nextNode, route, routeNodes };\n}\n\nexport function describeViewerGraphDensity(graph = {}) {\n  const edgeCount = Array.isArray(graph.edges) ? graph.edges.length : 0;\n  const nodeCount = Array.isArray(graph.nodes) ? graph.nodes.length : 0;\n  const incidentCounts = new Map();\n  for (const edge of graph.edges || []) {\n    incidentCounts.set(edge.source?.id, (incidentCounts.get(edge.source?.id) || 0) + 1);\n    incidentCounts.set(edge.target?.id, (incidentCounts.get(edge.target?.id) || 0) + 1);\n  }\n  const maxIncident = Math.max(0, ...incidentCounts.values(), 0);\n  const dense = edgeCount >= 120 || nodeCount >= 140 || maxIncident >= 70;\n  return {\n    mode: dense ? \"dense\" : \"normal\",\n    edgeCount,\n    nodeCount,\n    maxIncident,\n    incidentCounts\n  };\n}\n\nexport function selectViewerLabeledNodes(graph = {}, options = {}) {\n  const dense = options.dense === true;\n  const maxDenseLabels = Number(options.maxDenseLabels || 24);\n  const nodes = Array.isArray(graph.nodes) ? graph.nodes : [];\n  if (!dense) {\n    return new Set(nodes.map((node) => node.id || node.key).filter(Boolean));\n  }\n  const incidentCounts = describeViewerGraphDensity(graph).incidentCounts;\n  const ranked = [...nodes]\n    .sort((a, b) => {\n      const aSelected = a.selected ? 1 : 0;\n      const bSelected = b.selected ? 1 : 0;\n      if (aSelected !== bSelected) return bSelected - aSelected;\n      const aDistance = Number(a.distance || 0);\n      const bDistance = Number(b.distance || 0);\n      if (aDistance !== bDistance) return aDistance - bDistance;\n      const aIncident = incidentCounts.get(a.id) || 0;\n      const bIncident = incidentCounts.get(b.id) || 0;\n      if (aIncident !== bIncident) return bIncident - aIncident;\n      return Number(b.importance || 0) - Number(a.importance || 0);\n    });\n  const visible = new Set();\n  for (const node of ranked) {\n    if (node.selected) visible.add(node.id || node.key);\n  }\n  for (const node of ranked) {\n    const id = node.id || node.key;\n    if (!id) continue;\n    if (Number(node.distance || 0) <= 1 && visible.size < maxDenseLabels) visible.add(id);\n    if (visible.size >= maxDenseLabels) break;\n  }\n  return visible;\n}\n\nexport function pickNextViewerTourNode(options = {}) {\n  const {\n    nodes = [],\n    focusId = \"\",\n    previousFocusId = \"\",\n    tourRecent = [],\n    tourVisited = [],\n    tourIndex = 0\n  } = options;\n\n  const visibleNodes = nodes.filter((node) => node.id !== focusId);\n  const localNodes = visibleNodes.filter((node) => node.distance === 1 || node.distance === 2);\n  const basePool = localNodes.length ? localNodes : visibleNodes;\n  const recent = new Set(tourRecent || []);\n  const visited = tourVisited instanceof Set ? tourVisited : new Set(tourVisited || []);\n  const fresh = basePool.filter((node) => !visited.has(node.id) && !recent.has(node.id));\n  const notRecent = basePool.filter((node) => !recent.has(node.id) && node.id !== previousFocusId);\n  const pool = (fresh.length ? fresh : notRecent.length ? notRecent : basePool)\n    .sort((a, b) => {\n      const aDistance = a.distance || 3;\n      const bDistance = b.distance || 3;\n      if (aDistance !== bDistance) return aDistance - bDistance;\n      return Number(b.importance || 3) - Number(a.importance || 3);\n    });\n\n  if (!pool.length) {\n    return { nextId: null, nextIndex: tourIndex };\n  }\n\n  const normalizedIndex = tourIndex % pool.length;\n  const next = pool[normalizedIndex];\n  return {\n    nextId: next?.id || null,\n    nextIndex: (normalizedIndex + 1) % pool.length\n  };\n}\n\nexport function advanceViewerPlaybackState(options = {}) {\n  const {\n    tourActive = false,\n    activeTrail = null,\n    focusId = \"\",\n    previousFocusId = \"\",\n    tourRecent = [],\n    tourVisited = [],\n    tourIndex = 0,\n    nodes = []\n  } = options;\n\n  if (activeTrail?.nodes?.length) {\n    const choice = pickNextViewerTrailNode(activeTrail, focusId, options);\n    if (choice.branch) {\n      return {\n        kind: \"branch\",\n        nextId: null,\n        nextIndex: tourIndex,\n        activeTrail: choice.trail,\n        branch: choice.branch,\n        stopTour: false,\n        stopTrail: false\n      };\n    }\n    if (!choice.nextId) {\n      return {\n        kind: tourActive ? \"stop-tour\" : \"stop-trail\",\n        nextId: null,\n        nextIndex: tourIndex,\n        activeTrail: choice.trail,\n        branch: null,\n        stopTour: tourActive,\n        stopTrail: !tourActive\n      };\n    }\n    return {\n      kind: \"node\",\n      nextId: choice.nextId,\n      nextIndex: tourIndex,\n      activeTrail: choice.trail,\n      branch: null,\n      stopTour: false,\n      stopTrail: false\n    };\n  }\n\n  const choice = pickNextViewerTourNode({\n    ...options,\n    nodes,\n    focusId,\n    previousFocusId,\n    tourRecent,\n    tourVisited,\n    tourIndex\n  });\n  if (!choice.nextId) {\n    return {\n      kind: \"stop-tour\",\n      nextId: null,\n      nextIndex: tourIndex,\n      activeTrail,\n      branch: null,\n      stopTour: true,\n      stopTrail: false\n    };\n  }\n\n  return {\n    kind: \"node\",\n    nextId: choice.nextId,\n    nextIndex: choice.nextIndex,\n    activeTrail,\n    branch: null,\n    stopTour: false,\n    stopTrail: false\n  };\n}\n\nfunction buildViewerPathGraph(allEdges = [], allowReverse = true) {\n  const adjacency = new Map();\n  const addEdge = (fromId, toId, edge, reversed) => {\n    if (!adjacency.has(fromId)) adjacency.set(fromId, []);\n    adjacency.get(fromId).push({ toId, edge, reversed });\n  };\n\n  allEdges.forEach((edge, index) => {\n    const normalizedEdge = { ...edge, _edgeIndex: index };\n    addEdge(normalizedEdge.source, normalizedEdge.target, normalizedEdge, false);\n    if (allowReverse) addEdge(normalizedEdge.target, normalizedEdge.source, normalizedEdge, true);\n  });\n\n  return adjacency;\n}\n\nfunction viewerRelationshipStoryPriority(type) {\n  const priorities = {\n    defines: 10,\n    has_claim: 10,\n    supports: 9,\n    evidence_for: 9,\n    derived_from: 9,\n    authored: 8,\n    created: 8,\n    influenced: 8,\n    implements: 8,\n    enables: 8,\n    contains: 8,\n    uses: 7,\n    explains: 7,\n    documents: 7,\n    context_for: 6,\n    continues_to: 6,\n    related_to: 2,\n    mentions: 1\n  };\n  return priorities[type] || 4;\n}\n\nexport function scoreViewerConnectivePath(path = {}) {\n  const hopCount = path.hops?.length || 1;\n  const edgeScore = (path.hops || []).reduce((sum, hop) => {\n    const edge = hop.edge || {};\n    const weight = Number(edge.weight || 1);\n    const visibility = edge.visibility === \"primary\" ? 8 : edge.visibility === \"secondary\" ? 4 : 0;\n    const directionPenalty = hop.reversed ? -1 : 0;\n    return sum + weight * 6 + visibility + viewerRelationshipStoryPriority(edge.type) + directionPenalty;\n  }, 0);\n  return edgeScore - hopCount * 5;\n}\n\nexport function findViewerConnectivePaths(allEdges = [], sourceId = \"\", targetId = \"\", options = {}) {\n  const allowReverse = options.allowReverse !== false;\n  const maxDepth = Number(options.maxDepth || 6);\n  const maxPaths = Number(options.maxPaths || 6);\n  const searchLimit = Math.max(maxPaths * 12, 48);\n  const adjacency = buildViewerPathGraph(allEdges, allowReverse);\n  const results = [];\n  const visited = new Set([sourceId]);\n  const path = [];\n  const pathNodeIds = [sourceId];\n\n  const dfs = (currentId, depth) => {\n    if (results.length >= searchLimit) return;\n    if (depth > maxDepth) return;\n\n    if (currentId === targetId) {\n      results.push({\n        nodes: [...pathNodeIds],\n        hops: path.map((step) => ({ ...step }))\n      });\n      return;\n    }\n\n    const neighbors = adjacency.get(currentId) || [];\n    for (const step of neighbors) {\n      if (visited.has(step.toId)) continue;\n      visited.add(step.toId);\n      path.push({\n        fromId: currentId,\n        toId: step.toId,\n        edge: step.edge,\n        reversed: step.reversed\n      });\n      pathNodeIds.push(step.toId);\n      dfs(step.toId, depth + 1);\n      pathNodeIds.pop();\n      path.pop();\n      visited.delete(step.toId);\n      if (results.length >= searchLimit) return;\n    }\n  };\n\n  dfs(sourceId, 0);\n\n  return results\n    .sort((a, b) => {\n      const scoreDiff = scoreViewerConnectivePath(b) - scoreViewerConnectivePath(a);\n      if (scoreDiff) return scoreDiff;\n      if (a.hops.length !== b.hops.length) return a.hops.length - b.hops.length;\n      return a.nodes.join(\" \").localeCompare(b.nodes.join(\" \"));\n    })\n    .slice(0, maxPaths);\n}\n\nexport function viewerRelationshipPhrase(type, reversed = false) {\n  const forwardPhrases = {\n    supports: \"supports\",\n    contradicts: \"contradicts\",\n    explains: \"explains\",\n    defines: \"defines\",\n    has_claim: \"has claim\",\n    claim_of: \"is a claim of\",\n    demonstrates: \"demonstrates\",\n    derives_from: \"derives from\",\n    derived_from: \"derives from\",\n    cites: \"cites\",\n    quotes: \"quotes\",\n    mentions: \"mentions\",\n    references: \"references\",\n    documents: \"documents\",\n    authored: \"authored\",\n    authored_by: \"was authored by\",\n    created: \"created\",\n    created_by: \"was created by\",\n    participated_in: \"participated in\",\n    spoke_at: \"spoke at\",\n    features: \"features\",\n    presented: \"presented\",\n    introduced: \"introduced\",\n    proposed: \"proposed\",\n    influenced: \"influenced\",\n    influenced_by: \"was influenced by\",\n    popularized: \"popularized\",\n    anticipated: \"anticipated\",\n    anticipates: \"anticipates\",\n    shaped: \"shaped\",\n    shapes: \"shapes\",\n    implements: \"implements\",\n    implemented_by: \"is implemented by\",\n    enables: \"enables\",\n    preserves: \"preserves\",\n    transcludes: \"transcludes\",\n    deep_links_to: \"deep-links to\",\n    has_primary_media: \"has primary media\",\n    used_as_primary_media_for: \"is used as primary media for\",\n    context_for: \"gives context for\",\n    has_context: \"has context from\",\n    continues_to: \"continues to\",\n    continued_from: \"continues from\",\n    starts_with: \"starts with\",\n    started_by: \"is started by\",\n    example_of: \"is an example of\",\n    part_of: \"is part of\",\n    contains: \"contains\",\n    uses: \"uses\",\n    used_by: \"is used by\",\n    related_to: \"relates to\"\n  };\n\n  if (!reversed) return forwardPhrases[type] || String(type || \"relates_to\").replace(/_/g, \" \");\n  const reversePhrases = {\n    supports: \"is supported by\",\n    contradicts: \"is contradicted by\",\n    explains: \"is explained by\",\n    defines: \"is defined by\",\n    demonstrates: \"is demonstrated by\",\n    cites: \"is cited by\",\n    quotes: \"is quoted by\",\n    mentions: \"is mentioned by\",\n    references: \"is referenced by\",\n    documents: \"is documented by\",\n    features: \"is featured in\",\n    presented: \"was presented by\",\n    proposed: \"was proposed by\",\n    introduced: \"was introduced by\",\n    popularized: \"was popularized by\",\n    enables: \"is enabled by\",\n    preserves: \"is preserved by\",\n    transcludes: \"is transcluded by\",\n    deep_links_to: \"is deep-linked by\",\n    continues_to: \"was continued from\",\n    starts_with: \"is started by\",\n    contains: \"is contained by\",\n    uses: \"is used by\",\n    related_to: \"relates to\"\n  };\n  return reversePhrases[type] || `is ${String(type || \"related_to\").replace(/_/g, \" \")} by`;\n}\n\nexport function buildViewerPathStory(path = {}, nodeById = new Map()) {\n  const parts = (path.hops || []).map((hop, index) => {\n    const fromNode = nodeById.get(hop.fromId);\n    const toNode = nodeById.get(hop.toId);\n    const fromTitle = String(fromNode?.title || hop.fromId || \"\").trim();\n    const toTitle = String(toNode?.title || hop.toId || \"\").trim();\n    const phrase = viewerRelationshipPhrase(hop.edge?.type || \"related_to\", hop.reversed);\n    const lead = index === 0 ? \"\" : \"Then \";\n    return `${lead}${fromTitle} ${phrase} ${toTitle}`;\n  });\n  return parts.length ? `${parts.join(\". \")}.` : \"\";\n}\n",
  "source_snapshot": {
    "captured_at": "2026-06-30T05:09:29.991Z",
    "source_url": "https://github.com/kingc95/XanaNode-Hugo/blob/main/static/js/viewer-engine.js",
    "method": "archive",
    "content_id": "sha256:cc3858cedd795c5a60fac24a0c926050188da69114a9b02c455cff7759931cc0",
    "rights_status": "Apache-2.0",
    "tool": "xananode-hugo/tools/build-substrate-source.mjs"
  },
  "relationships": []
}
