{
  "id": "xananode.hugo:source/artifact-static-schemas-xananode-node-types-v0-3-0",
  "title": "Static / Schemas / Xananode Node Types.V0.3.0",
  "type": "source",
  "subtype": "renderer_asset",
  "importance": 3,
  "summary": "static/schemas/xananode-node-types.v0.3.0.json is preserved as a raw Hugo source artifact in the XanaNode Hugo substrate.",
  "source_url": "https://github.com/kingc95/XanaNode-Hugo/blob/main/static/schemas/xananode-node-types.v0.3.0.json",
  "artifact_path": "static/schemas/xananode-node-types.v0.3.0.json",
  "asset_path": "assets/raw/repository/static/schemas/xananode-node-types.v0.3.0.json",
  "asset_role": "repository_source",
  "media_type": "document",
  "mime_type": "application/json",
  "rights_status": "Apache-2.0",
  "content_id": "sha256:5b6fdc89ffafe73cd2b0d9fd78a49cd65692ddc5f752e9ed2b1965eb6bbd6be4",
  "content": "{\r\n  \"version\": \"0.3.0\",\r\n  \"node_types\": [\r\n    {\r\n      \"type\": \"person\",\r\n      \"label\": \"Person\",\r\n      \"color\": {\r\n        \"bg\": \"#8bd3ff\",\r\n        \"fg\": \"#071827\",\r\n        \"outline\": \"#d8f1ff\"\r\n      },\r\n      \"purpose\": \"A human actor who created, influenced, witnessed, argued, documented, or participated in something.\",\r\n      \"allowed_subtypes\": [\r\n        \"writer\",\r\n        \"researcher\",\r\n        \"engineer\",\r\n        \"critic\",\r\n        \"artist\",\r\n        \"founder\",\r\n        \"scientist\",\r\n        \"programmer\"\r\n      ],\r\n      \"required_frontmatter\": [\r\n        \"title\",\r\n        \"type\",\r\n        \"importance\",\r\n        \"summary\",\r\n        \"relationships\"\r\n      ],\r\n      \"recommended_frontmatter\": [\r\n        \"roles\",\r\n        \"primary_media\",\r\n        \"people\",\r\n        \"concepts\",\r\n        \"sources\",\r\n        \"projects\",\r\n        \"events\"\r\n      ],\r\n      \"namespace\": \"xananode\",\r\n      \"id\": \"xananode:person\",\r\n      \"core\": true,\r\n      \"extends\": null\r\n    },\r\n    {\r\n      \"type\": \"concept\",\r\n      \"label\": \"Concept\",\r\n      \"color\": {\r\n        \"bg\": \"#91f2a6\",\r\n        \"fg\": \"#062010\",\r\n        \"outline\": \"#dcffe4\"\r\n      },\r\n      \"purpose\": \"An idea, pattern, theory, failure mode, or explanatory structure. A concept is built from claims.\",\r\n      \"allowed_subtypes\": [\r\n        \"theory\",\r\n        \"principle\",\r\n        \"failure_mode\",\r\n        \"method\",\r\n        \"pattern\",\r\n        \"distinction\",\r\n        \"frame\"\r\n      ],\r\n      \"required_frontmatter\": [\r\n        \"title\",\r\n        \"type\",\r\n        \"importance\",\r\n        \"summary\",\r\n        \"relationships\"\r\n      ],\r\n      \"recommended_frontmatter\": [\r\n        \"claims\",\r\n        \"concepts\",\r\n        \"sources\",\r\n        \"people\",\r\n        \"projects\"\r\n      ],\r\n      \"namespace\": \"xananode\",\r\n      \"id\": \"xananode:concept\",\r\n      \"core\": true,\r\n      \"extends\": null\r\n    },\r\n    {\r\n      \"type\": \"claim\",\r\n      \"label\": \"Claim\",\r\n      \"color\": {\r\n        \"bg\": \"#ff6b6b\",\r\n        \"fg\": \"#1a0000\",\r\n        \"outline\": \"#ffe0e0\"\r\n      },\r\n      \"purpose\": \"A specific assertion that can be supported, disputed, revised, deprecated, or rejected.\",\r\n      \"allowed_subtypes\": [\r\n        \"definition\",\r\n        \"historical\",\r\n        \"causal\",\r\n        \"interpretive\",\r\n        \"predictive\",\r\n        \"normative\",\r\n        \"comparative\"\r\n      ],\r\n      \"required_frontmatter\": [\r\n        \"title\",\r\n        \"type\",\r\n        \"importance\",\r\n        \"summary\",\r\n        \"status\",\r\n        \"relationships\"\r\n      ],\r\n      \"recommended_frontmatter\": [\r\n        \"confidence\",\r\n        \"claim_type\",\r\n        \"evidence\",\r\n        \"counterevidence\",\r\n        \"concepts\",\r\n        \"sources\"\r\n      ],\r\n      \"namespace\": \"xananode\",\r\n      \"id\": \"xananode:claim\",\r\n      \"core\": true,\r\n      \"extends\": null\r\n    },\r\n    {\r\n      \"type\": \"source\",\r\n      \"label\": \"Source\",\r\n      \"color\": {\r\n        \"bg\": \"#ff9f7a\",\r\n        \"fg\": \"#2a1208\",\r\n        \"outline\": \"#ffe4d9\"\r\n      },\r\n      \"purpose\": \"A reference work, transcript, paper, book, talk, article, dataset, or primary evidence item.\",\r\n      \"allowed_subtypes\": [\r\n        \"book\",\r\n        \"paper\",\r\n        \"article\",\r\n        \"transcript\",\r\n        \"talk\",\r\n        \"interview\",\r\n        \"dataset\",\r\n        \"website\",\r\n        \"official_site\",\r\n        \"documentation\",\r\n        \"git_repository\",\r\n        \"social_profile\",\r\n        \"support_page\",\r\n        \"web_snapshot\",\r\n        \"archive\"\r\n      ],\r\n      \"required_frontmatter\": [\r\n        \"title\",\r\n        \"type\",\r\n        \"importance\",\r\n        \"summary\",\r\n        \"relationships\"\r\n      ],\r\n      \"recommended_frontmatter\": [\r\n        \"author\",\r\n        \"year\",\r\n        \"source_url\",\r\n        \"archive_url\",\r\n        \"license\",\r\n        \"rights_status\"\r\n      ],\r\n      \"namespace\": \"xananode\",\r\n      \"id\": \"xananode:source\",\r\n      \"core\": true,\r\n      \"extends\": null\r\n    },\r\n    {\r\n      \"type\": \"essay\",\r\n      \"label\": \"Essay\",\r\n      \"color\": {\r\n        \"bg\": \"#f59ec3\",\r\n        \"fg\": \"#1f1020\",\r\n        \"outline\": \"#ffe3f0\"\r\n      },\r\n      \"purpose\": \"A human-authored argument that connects claims, sources, observations, and concepts.\",\r\n      \"allowed_subtypes\": [\r\n        \"argument\",\r\n        \"explainer\",\r\n        \"critique\",\r\n        \"manifesto\",\r\n        \"analysis\",\r\n        \"reflection\"\r\n      ],\r\n      \"required_frontmatter\": [\r\n        \"title\",\r\n        \"type\",\r\n        \"importance\",\r\n        \"summary\",\r\n        \"relationships\"\r\n      ],\r\n      \"recommended_frontmatter\": [\r\n        \"claims\",\r\n        \"concepts\",\r\n        \"people\",\r\n        \"sources\",\r\n        \"observations\"\r\n      ],\r\n      \"namespace\": \"xananode\",\r\n      \"id\": \"xananode:essay\",\r\n      \"core\": true,\r\n      \"extends\": null\r\n    },\r\n    {\r\n      \"type\": \"observation\",\r\n      \"label\": \"Observation\",\r\n      \"color\": {\r\n        \"bg\": \"#ef476f\",\r\n        \"fg\": \"#2a0610\",\r\n        \"outline\": \"#ffd7e0\"\r\n      },\r\n      \"purpose\": \"A real-world case, symptom, example, incident, failure, or pattern being analyzed.\",\r\n      \"allowed_subtypes\": [\r\n        \"case_study\",\r\n        \"failure\",\r\n        \"news_event\",\r\n        \"symptom\",\r\n        \"anomaly\",\r\n        \"example\"\r\n      ],\r\n      \"required_frontmatter\": [\r\n        \"title\",\r\n        \"type\",\r\n        \"importance\",\r\n        \"summary\",\r\n        \"relationships\"\r\n      ],\r\n      \"recommended_frontmatter\": [\r\n        \"observed_date\",\r\n        \"source_url\",\r\n        \"concepts\",\r\n        \"claims\",\r\n        \"sources\"\r\n      ],\r\n      \"namespace\": \"xananode\",\r\n      \"id\": \"xananode:observation\",\r\n      \"core\": true,\r\n      \"extends\": null\r\n    },\r\n    {\r\n      \"type\": \"media\",\r\n      \"label\": \"Media\",\r\n      \"color\": {\r\n        \"bg\": \"#55d6be\",\r\n        \"fg\": \"#04201a\",\r\n        \"outline\": \"#dcfff8\"\r\n      },\r\n      \"purpose\": \"An image, video, audio clip, screenshot, diagram, document, or other media item with provenance.\",\r\n      \"allowed_subtypes\": [\r\n        \"image\",\r\n        \"video\",\r\n        \"audio\",\r\n        \"document\",\r\n        \"screenshot\",\r\n        \"diagram\",\r\n        \"clip\",\r\n        \"scan\",\r\n        \"logo\",\r\n        \"thumbnail\",\r\n        \"web_snapshot\",\r\n        \"source_snapshot\"\r\n      ],\r\n      \"required_frontmatter\": [\r\n        \"title\",\r\n        \"type\",\r\n        \"media_type\",\r\n        \"importance\",\r\n        \"summary\",\r\n        \"alt\",\r\n        \"rights_status\",\r\n        \"relationships\"\r\n      ],\r\n      \"recommended_frontmatter\": [\r\n        \"file\",\r\n        \"asset_path\",\r\n        \"asset_role\",\r\n        \"mime_type\",\r\n        \"caption\",\r\n        \"creator\",\r\n        \"created_date\",\r\n        \"source_name\",\r\n        \"source_url\",\r\n        \"license\",\r\n        \"license_url\",\r\n        \"depicts\"\r\n      ],\r\n      \"namespace\": \"xananode\",\r\n      \"id\": \"xananode:media\",\r\n      \"core\": true,\r\n      \"extends\": null\r\n    },\r\n    {\r\n      \"type\": \"event\",\r\n      \"label\": \"Event\",\r\n      \"color\": {\r\n        \"bg\": \"#f59e0b\",\r\n        \"fg\": \"#1a0a00\",\r\n        \"outline\": \"#fff3e0\"\r\n      },\r\n      \"purpose\": \"Something that happened at a time and optionally at a place.\",\r\n      \"allowed_subtypes\": [\r\n        \"conference\",\r\n        \"talk\",\r\n        \"publication_event\",\r\n        \"meeting\",\r\n        \"release\",\r\n        \"incident\",\r\n        \"historical_event\"\r\n      ],\r\n      \"required_frontmatter\": [\r\n        \"title\",\r\n        \"type\",\r\n        \"importance\",\r\n        \"summary\",\r\n        \"relationships\"\r\n      ],\r\n      \"recommended_frontmatter\": [\r\n        \"date\",\r\n        \"start_date\",\r\n        \"end_date\",\r\n        \"place\",\r\n        \"people\",\r\n        \"organizations\",\r\n        \"sources\"\r\n      ],\r\n      \"namespace\": \"xananode\",\r\n      \"id\": \"xananode:event\",\r\n      \"core\": true,\r\n      \"extends\": null\r\n    },\r\n    {\r\n      \"type\": \"place\",\r\n      \"label\": \"Place\",\r\n      \"color\": {\r\n        \"bg\": \"#84cc16\",\r\n        \"fg\": \"#0a1a00\",\r\n        \"outline\": \"#e8ffe0\"\r\n      },\r\n      \"purpose\": \"A physical or virtual location where people, projects, organizations, or events exist or occurred.\",\r\n      \"allowed_subtypes\": [\r\n        \"city\",\r\n        \"building\",\r\n        \"lab\",\r\n        \"institution_site\",\r\n        \"online_space\",\r\n        \"country\",\r\n        \"region\"\r\n      ],\r\n      \"required_frontmatter\": [\r\n        \"title\",\r\n        \"type\",\r\n        \"importance\",\r\n        \"summary\",\r\n        \"relationships\"\r\n      ],\r\n      \"recommended_frontmatter\": [\r\n        \"location\",\r\n        \"geo\",\r\n        \"organizations\",\r\n        \"events\",\r\n        \"projects\"\r\n      ],\r\n      \"namespace\": \"xananode\",\r\n      \"id\": \"xananode:place\",\r\n      \"core\": true,\r\n      \"extends\": null\r\n    },\r\n    {\r\n      \"type\": \"organization\",\r\n      \"label\": \"Organization\",\r\n      \"color\": {\r\n        \"bg\": \"#f0abfc\",\r\n        \"fg\": \"#1e1028\",\r\n        \"outline\": \"#fde8ff\"\r\n      },\r\n      \"purpose\": \"A company, institution, agency, lab, school, collective, standards body, nonprofit, or group.\",\r\n      \"allowed_subtypes\": [\r\n        \"company\",\r\n        \"university\",\r\n        \"lab\",\r\n        \"agency\",\r\n        \"nonprofit\",\r\n        \"standards_body\",\r\n        \"publisher\"\r\n      ],\r\n      \"required_frontmatter\": [\r\n        \"title\",\r\n        \"type\",\r\n        \"importance\",\r\n        \"summary\",\r\n        \"relationships\"\r\n      ],\r\n      \"recommended_frontmatter\": [\r\n        \"website\",\r\n        \"founded\",\r\n        \"people\",\r\n        \"projects\",\r\n        \"technologies\"\r\n      ],\r\n      \"namespace\": \"xananode\",\r\n      \"id\": \"xananode:organization\",\r\n      \"core\": true,\r\n      \"extends\": null\r\n    },\r\n    {\r\n      \"type\": \"project\",\r\n      \"label\": \"Project\",\r\n      \"color\": {\r\n        \"bg\": \"#ffd166\",\r\n        \"fg\": \"#1d1500\",\r\n        \"outline\": \"#fff0c2\"\r\n      },\r\n      \"purpose\": \"A built, proposed, fictional, abandoned, or active system with a purpose and lineage.\",\r\n      \"allowed_subtypes\": [\r\n        \"software\",\r\n        \"research_project\",\r\n        \"fictional_system\",\r\n        \"prototype\",\r\n        \"standard\",\r\n        \"platform\"\r\n      ],\r\n      \"required_frontmatter\": [\r\n        \"title\",\r\n        \"type\",\r\n        \"importance\",\r\n        \"summary\",\r\n        \"relationships\"\r\n      ],\r\n      \"recommended_frontmatter\": [\r\n        \"status\",\r\n        \"people\",\r\n        \"organizations\",\r\n        \"technologies\",\r\n        \"sources\"\r\n      ],\r\n      \"namespace\": \"xananode\",\r\n      \"id\": \"xananode:project\",\r\n      \"core\": true,\r\n      \"extends\": null\r\n    },\r\n    {\r\n      \"type\": \"technology\",\r\n      \"label\": \"Technology\",\r\n      \"color\": {\r\n        \"bg\": \"#06b6d4\",\r\n        \"fg\": \"#04131a\",\r\n        \"outline\": \"#d9fbff\"\r\n      },\r\n      \"purpose\": \"A tool, protocol, model, platform, architecture, method, or technical system.\",\r\n      \"allowed_subtypes\": [\r\n        \"protocol\",\r\n        \"language\",\r\n        \"model\",\r\n        \"platform\",\r\n        \"architecture\",\r\n        \"tool\",\r\n        \"format\",\r\n        \"algorithm\"\r\n      ],\r\n      \"required_frontmatter\": [\r\n        \"title\",\r\n        \"type\",\r\n        \"importance\",\r\n        \"summary\",\r\n        \"relationships\"\r\n      ],\r\n      \"recommended_frontmatter\": [\r\n        \"projects\",\r\n        \"organizations\",\r\n        \"sources\",\r\n        \"concepts\"\r\n      ],\r\n      \"namespace\": \"xananode\",\r\n      \"id\": \"xananode:technology\",\r\n      \"core\": true,\r\n      \"extends\": null\r\n    },\r\n    {\r\n      \"type\": \"publication\",\r\n      \"label\": \"Publication\",\r\n      \"color\": {\r\n        \"bg\": \"#a78bfa\",\r\n        \"fg\": \"#140f22\",\r\n        \"outline\": \"#ede3ff\"\r\n      },\r\n      \"purpose\": \"A released intellectual or creative work such as a book, article, paper, film, episode, or talk.\",\r\n      \"allowed_subtypes\": [\r\n        \"book\",\r\n        \"paper\",\r\n        \"article\",\r\n        \"film\",\r\n        \"episode\",\r\n        \"talk\",\r\n        \"podcast\",\r\n        \"webpage\"\r\n      ],\r\n      \"required_frontmatter\": [\r\n        \"title\",\r\n        \"type\",\r\n        \"importance\",\r\n        \"summary\",\r\n        \"relationships\"\r\n      ],\r\n      \"recommended_frontmatter\": [\r\n        \"author\",\r\n        \"publisher\",\r\n        \"year\",\r\n        \"source_url\",\r\n        \"license\",\r\n        \"rights_status\"\r\n      ],\r\n      \"namespace\": \"xananode\",\r\n      \"id\": \"xananode:publication\",\r\n      \"core\": true,\r\n      \"extends\": null\r\n    },\r\n    {\r\n      \"type\": \"community\",\r\n      \"label\": \"Community\",\r\n      \"color\": {\r\n        \"bg\": \"#fb923c\",\r\n        \"fg\": \"#201006\",\r\n        \"outline\": \"#ffe7d6\"\r\n      },\r\n      \"purpose\": \"A group organized around an identity, platform, shared work, practice, interest, or tradition.\",\r\n      \"allowed_subtypes\": [\r\n        \"forum\",\r\n        \"professional\",\r\n        \"open_source\",\r\n        \"fan\",\r\n        \"research\",\r\n        \"local\",\r\n        \"online\"\r\n      ],\r\n      \"required_frontmatter\": [\r\n        \"title\",\r\n        \"type\",\r\n        \"importance\",\r\n        \"summary\",\r\n        \"relationships\"\r\n      ],\r\n      \"recommended_frontmatter\": [\r\n        \"website\",\r\n        \"people\",\r\n        \"projects\",\r\n        \"events\"\r\n      ],\r\n      \"namespace\": \"xananode\",\r\n      \"id\": \"xananode:community\",\r\n      \"core\": true,\r\n      \"extends\": null\r\n    },\r\n    {\r\n      \"type\": \"relationship\",\r\n      \"label\": \"Relationship\",\r\n      \"color\": {\r\n        \"bg\": \"#ec4899\",\r\n        \"fg\": \"#240812\",\r\n        \"outline\": \"#ffd8ea\"\r\n      },\r\n      \"purpose\": \"A first-class edge treated as a node because the relationship itself has history, evidence, dispute, or explanation.\",\r\n      \"allowed_subtypes\": [\r\n        \"friendship\",\r\n        \"influence\",\r\n        \"collaboration\",\r\n        \"citation\",\r\n        \"dispute\",\r\n        \"lineage\",\r\n        \"dependency\"\r\n      ],\r\n      \"required_frontmatter\": [\r\n        \"title\",\r\n        \"type\",\r\n        \"importance\",\r\n        \"summary\",\r\n        \"source_node\",\r\n        \"target_node\",\r\n        \"relationship_type\",\r\n        \"relationships\"\r\n      ],\r\n      \"recommended_frontmatter\": [\r\n        \"evidence\",\r\n        \"confidence\",\r\n        \"status\",\r\n        \"asserted_by\",\r\n        \"reviewed_by\"\r\n      ],\r\n      \"namespace\": \"xananode\",\r\n      \"id\": \"xananode:relationship\",\r\n      \"core\": true,\r\n      \"extends\": null\r\n    },\r\n    {\r\n      \"type\": \"revision\",\r\n      \"label\": \"Revision\",\r\n      \"color\": {\r\n        \"bg\": \"#94a3b8\",\r\n        \"fg\": \"#0f172a\",\r\n        \"outline\": \"#dde5f2\"\r\n      },\r\n      \"purpose\": \"An immutable historical version of another node.\",\r\n      \"allowed_subtypes\": [\r\n        \"node_revision\",\r\n        \"claim_revision\",\r\n        \"relationship_revision\",\r\n        \"media_revision\"\r\n      ],\r\n      \"required_frontmatter\": [\r\n        \"title\",\r\n        \"type\",\r\n        \"importance\",\r\n        \"summary\",\r\n        \"revises\",\r\n        \"revision_id\",\r\n        \"relationships\"\r\n      ],\r\n      \"recommended_frontmatter\": [\r\n        \"created_by\",\r\n        \"created_date\",\r\n        \"supersedes\",\r\n        \"superseded_by\",\r\n        \"change_summary\"\r\n      ],\r\n      \"namespace\": \"xananode\",\r\n      \"id\": \"xananode:revision\",\r\n      \"core\": true,\r\n      \"extends\": null\r\n    },\r\n    {\r\n      \"type\": \"trail\",\r\n      \"label\": \"Trail\",\r\n      \"color\": {\r\n        \"bg\": \"#fb8500\",\r\n        \"fg\": \"#241100\",\r\n        \"outline\": \"#ffe3be\"\r\n      },\r\n      \"purpose\": \"A curated route through the graph.\",\r\n      \"allowed_subtypes\": [\r\n        \"introductory\",\r\n        \"historical\",\r\n        \"argument\",\r\n        \"evidence_path\",\r\n        \"teaching_path\",\r\n        \"dispute_path\"\r\n      ],\r\n      \"required_frontmatter\": [\r\n        \"title\",\r\n        \"type\",\r\n        \"importance\",\r\n        \"summary\",\r\n        \"nodes\",\r\n        \"relationships\"\r\n      ],\r\n      \"recommended_frontmatter\": [\r\n        \"concepts\",\r\n        \"people\",\r\n        \"sources\",\r\n        \"claims\"\r\n      ],\r\n      \"namespace\": \"xananode\",\r\n      \"id\": \"xananode:trail\",\r\n      \"core\": true,\r\n      \"extends\": null\r\n    },\r\n    {\r\n      \"type\": \"schema\",\r\n      \"label\": \"Schema\",\r\n      \"color\": {\r\n        \"bg\": \"#e2e8f0\",\r\n        \"fg\": \"#111827\",\r\n        \"outline\": \"#ffffff\"\r\n      },\r\n      \"purpose\": \"A rule, ontology, validation document, or governance definition used by XanaNode itself.\",\r\n      \"allowed_subtypes\": [\r\n        \"node_type_schema\",\r\n        \"relationship_type_schema\",\r\n        \"validation_rule\",\r\n        \"governance_rule\",\r\n        \"style_rule\"\r\n      ],\r\n      \"required_frontmatter\": [\r\n        \"title\",\r\n        \"type\",\r\n        \"importance\",\r\n        \"summary\",\r\n        \"relationships\"\r\n      ],\r\n      \"recommended_frontmatter\": [\r\n        \"version\",\r\n        \"status\",\r\n        \"source_url\"\r\n      ],\r\n      \"namespace\": \"xananode\",\r\n      \"id\": \"xananode:schema\",\r\n      \"core\": true,\r\n      \"extends\": null\r\n    },\r\n    {\r\n      \"namespace\": \"xananode\",\r\n      \"id\": \"xananode:fragment\",\r\n      \"type\": \"fragment\",\r\n      \"label\": \"Fragment\",\r\n      \"color\": {\r\n        \"bg\": \"#38bdf8\",\r\n        \"fg\": \"#03131f\",\r\n        \"outline\": \"#d8f4ff\"\r\n      },\r\n      \"purpose\": \"A stable, addressable portion of another node, source, media object, or publication used for deep linking, quotation, citation, transclusion, and revision-aware reference.\",\r\n      \"allowed_subtypes\": [\r\n        \"section\",\r\n        \"paragraph\",\r\n        \"sentence\",\r\n        \"quote\",\r\n        \"code_block\",\r\n        \"data_range\",\r\n        \"media_segment\",\r\n        \"image_region\"\r\n      ],\r\n      \"required_frontmatter\": [\r\n        \"title\",\r\n        \"type\",\r\n        \"importance\",\r\n        \"summary\",\r\n        \"source_node\",\r\n        \"fragment_id\",\r\n        \"relationships\"\r\n      ],\r\n      \"recommended_frontmatter\": [\r\n        \"tumbler\",\r\n        \"source_revision\",\r\n        \"content_hash\",\r\n        \"selector\",\r\n        \"start_offset\",\r\n        \"end_offset\",\r\n        \"byte_range\",\r\n        \"line_range\",\r\n        \"time_range\",\r\n        \"rights_status\"\r\n      ]\r\n    }\r\n  ]\r\n}\r\n",
  "source_snapshot": {
    "captured_at": "2026-06-25T14:22:34.827Z",
    "source_url": "https://github.com/kingc95/XanaNode-Hugo/blob/main/static/schemas/xananode-node-types.v0.3.0.json",
    "method": "archive",
    "content_id": "sha256:5b6fdc89ffafe73cd2b0d9fd78a49cd65692ddc5f752e9ed2b1965eb6bbd6be4",
    "rights_status": "Apache-2.0",
    "tool": "xananode-hugo/tools/build-substrate-source.mjs"
  },
  "relationships": []
}
