{
  "id": "xananode.example:essay/using-hugo-with-protocol-json",
  "protocol_id": "xananode.example:essay/using-hugo-with-protocol-json",
  "content_id": "sha256:70575ca5a1694a5391db26836daeddcd86a3a83ccacae96b774c2e11fea9f7f3",
  "version_id": "sha256:70575ca5a1694a5391db26836daeddcd86a3a83ccacae96b774c2e11fea9f7f3",
  "local_id": "using-hugo-with-protocol-json",
  "title": "Using Hugo with Protocol JSON",
  "type": "essay",
  "facets": [],
  "summary": "How to use the Hugo theme as a read-only XanaNode viewer for Markdown-authored nodes, the protocol base pack, and imported protocol JSON.",
  "importance": 5,
  "relationships": [
    {
      "id": "xananode.example:rel/xananode-example-essay-using-hugo-with-protocol-json-explains-xananode-hugo-theme-111",
      "type": "explains",
      "source": "xananode.example:essay/using-hugo-with-protocol-json",
      "target": "xananode-hugo-theme",
      "direction": "outgoing",
      "external": false
    },
    {
      "id": "xananode.example:rel/xananode-example-essay-using-hugo-with-protocol-json-explains-substrate-node-record-112",
      "type": "explains",
      "source": "xananode.example:essay/using-hugo-with-protocol-json",
      "target": "substrate-node-record",
      "direction": "outgoing",
      "external": false
    },
    {
      "id": "xananode.example:rel/xananode-example-essay-using-hugo-with-protocol-json-explains-substrate-relationship-list-113",
      "type": "explains",
      "source": "xananode.example:essay/using-hugo-with-protocol-json",
      "target": "substrate-relationship-list",
      "direction": "outgoing",
      "external": false
    },
    {
      "id": "xananode.example:rel/xananode-example-essay-using-hugo-with-protocol-json-context-for-historical-lineage-trail-114",
      "type": "context_for",
      "source": "xananode.example:essay/using-hugo-with-protocol-json",
      "target": "historical-lineage-trail",
      "direction": "outgoing",
      "external": false
    }
  ],
  "body": "\nHugo is the static publishing layer. It is not the protocol.\n\nUse Markdown when you want prose pages, essays, explainers, sources, or authored trails. Use protocol JSON when you already have validated substrate records from Core, Workspace, another tool, or another substrate.\n\nThe import path is intentionally simple. Drop a pack into the site, then let the prepare step merge it into the generated substrate:\n\n```text\nimports/\n  lineage/\n    nodes.json\n    relationships.json\n```\n\n`nodes.json` can contain either a single substrate node, an array of substrate nodes, or an object with a `nodes` array. `relationships.json` can contain either an array of relationships or an object with a `relationships` array.\n\nThe example site uses two packs:\n\n- `params.xananode.packs` in `hugo.yaml` mounts the protocol minimal substrate from the Core/Protocol submodule. It demonstrates the base model: substrate manifest, node records, typed relationships, evidence, stable fragments, and transclusion.\n- `imports/lineage/` extends that model with the fuller human-computer augmentation lineage: Leibniz, Otlet, Bush, Nelson, Engelbart, Brown, HES, FRESS, Intermedia, HyperCard, Hyperland, VR, TED2, the Web, and the XanaNode bridge concepts.\n\nMounted packs are build-time layers. They can be enabled or removed without claiming local ownership of their records. Absorbed packs are reviewed imports that become part of the receiving substrate. The base pack is mounted here so the protocol repository remains its governed source of truth.\n\nThen run:\n\n```bash\nnpm run validate\nnpm run build\n```\n\nThe prepare step validates the generated and imported records together, writes the protocol artifacts, and emits a browser-ready viewer feed.\n\nThe important published files are:\n\n```text\n/substrate.json\n/nodes-index.json\n/nodes/*.json\n/relationships.json\n/xananode-viewer.json\n```\n\n`/substrate.json`, `/nodes/*.json`, and `/relationships.json` are the protocol artifacts. `/nodes-index.json` makes the node files discoverable on a static host, because browsers cannot list a directory. `/xananode-viewer.json` is the read-only browser bundle derived from those protocol records.\n\nThat means you do not need to recreate imported records as Markdown just to see them. Markdown is for authored human pages. JSON imports are for existing protocol objects.\n\nCore remains responsible for protocol intelligence. During prepare, Hugo hands Core the existing substrate and the incoming packs so Core can report possible same-entity merges, relationships that touch existing nodes, possible links from prose to known nodes, and possible transclusions. Hugo is the renderer and static-site adapter; Core is where the reusable substrate analysis belongs.\n\nThis is the pattern for a new site: mount the base pack if you want a known-good skeleton, drop in generated JSON from Core or Workspace, write Markdown only where you want human-authored pages, then publish the generated protocol artifacts with the static viewer.\n",
  "source_file": "content/essays/using-hugo-with-protocol-json.md",
  "aliases": [],
  "tags": [],
  "outgoing_relationships": [
    "xananode.example:rel/xananode-example-essay-using-hugo-with-protocol-json-explains-xananode-hugo-theme-111",
    "xananode.example:rel/xananode-example-essay-using-hugo-with-protocol-json-explains-substrate-node-record-112",
    "xananode.example:rel/xananode-example-essay-using-hugo-with-protocol-json-explains-substrate-relationship-list-113",
    "xananode.example:rel/xananode-example-essay-using-hugo-with-protocol-json-context-for-historical-lineage-trail-114"
  ],
  "incoming_relationships": []
}
