{
  "id": "xananode.canonical:schema/merge-report-schema",
  "title": "Merge Report Schema",
  "type": "schema",
  "subtype": "validation_rule",
  "importance": 4,
  "summary": "The JSON Schema for reporting merge decisions, identity handling, conflicts, and intake outcomes between substrates.",
  "source_url": "https://github.com/kingc95/XanaNode-Protocol/blob/main/schemas/merge-report.schema.json",
  "relationships": [
    {
      "id": "xananode.canonical:rel/protocol-contains-merge-report-schema",
      "type": "contains",
      "source": "xananode.canonical:project/xananode-protocol",
      "direction": "incoming"
    }
  ],
  "imported_from": "nodes.json",
  "pack_id": "xananode.canonical",
  "pack_mode": "mounted"
}
