{
  "id": "xananode.example:concept/schema-extension",
  "title": "Schema Extension",
  "type": "concept",
  "importance": 4,
  "summary": "The ability for a substrate to add custom node or relationship types while remaining compatible with XanaNode Core.",
  "relationships": [
    {
      "id": "xananode.example:rel/xananode-core-schema-enables-schema-extension-36",
      "type": "enables",
      "source": "xananode.example:schema/xananode-core-schema",
      "direction": "incoming"
    },
    {
      "id": "xananode.example:rel/namespace-schema-required_for-schema-extension-48",
      "type": "required_for",
      "source": "xananode.example:schema/namespace-schema",
      "direction": "incoming"
    },
    {
      "id": "xananode.example:rel/schema-extension-enabled_by-namespacing-118",
      "type": "enabled_by",
      "target": "xananode.example:concept/namespacing",
      "direction": "outgoing"
    },
    {
      "id": "xananode.example:rel/schema-extension-requires-xananode-core-schema-119",
      "type": "requires",
      "target": "xananode.example:schema/xananode-core-schema",
      "direction": "outgoing"
    },
    {
      "id": "xananode.example:rel/schema-extension-required_for-federated-knowledge-substrates-120",
      "type": "required_for",
      "target": "xananode.example:concept/federated-knowledge-substrates",
      "direction": "outgoing"
    },
    {
      "id": "xananode.example:rel/namespacing-clarifies-schema-extension-130",
      "type": "clarifies",
      "source": "xananode.example:concept/namespacing",
      "direction": "incoming"
    },
    {
      "id": "xananode.example:rel/namespace-registry-required_for-schema-extension-132",
      "type": "required_for",
      "source": "xananode.example:concept/namespace-registry",
      "direction": "incoming"
    },
    {
      "id": "xananode.example:rel/merge-validation-requires-schema-extension-138",
      "type": "requires",
      "source": "xananode.example:concept/merge-validation",
      "direction": "incoming"
    },
    {
      "id": "xananode.example:rel/custom-extension-substrate-demonstrates-schema-extension-175",
      "type": "demonstrates",
      "source": "xananode.example:concept/custom-extension-substrate",
      "direction": "incoming"
    },
    {
      "id": "xananode.example:rel/canonical-type-policy-context_for-schema-extension-188",
      "type": "context_for",
      "source": "xananode.example:concept/canonical-type-policy",
      "direction": "incoming"
    }
  ]
}
